brainmapper/__init__.py
brainmapper-0.0.1.dist-info/LICENSE
brainmapper-0.0.1.dist-info/METADATA
brainmapper-0.0.1.dist-info/WHEEL
brainmapper-0.0.1.dist-info/top_level.txt
brainmapper-0.0.1.dist-info/RECORD
