Metadata-Version: 2.1
Name: brainmapper
Version: 0.0.1
Summary: Whole brain cell detection and atlas registration
Author-email: BrainGlobe developers <hello@brainglobe.info>
License: BSD-3-Clause
Project-URL: Homepage, https://github.com/brainglobe/brainmapper
Project-URL: Bug Tracker, https://github.com/brainglobe/brainmapper/issues
Project-URL: Documentation, https://github.com/brainglobe/brainmapper
Project-URL: Source Code, https://github.com/brainglobe/brainmapper
Project-URL: User Support, https://github.com/brainglobe/brainmapper/issues
Classifier: Development Status :: 2 - Pre-Alpha
Classifier: Programming Language :: Python
Classifier: Programming Language :: Python :: 3
Classifier: Programming Language :: Python :: 3.9
Classifier: Programming Language :: Python :: 3.10
Classifier: Programming Language :: Python :: 3.11
Classifier: Operating System :: OS Independent
Classifier: License :: OSI Approved :: BSD License
Requires-Python: >=3.9.0
License-File: LICENSE
Provides-Extra: dev
Requires-Dist: pytest ; extra == 'dev'
Requires-Dist: pytest-cov ; extra == 'dev'
Requires-Dist: coverage ; extra == 'dev'
Requires-Dist: tox ; extra == 'dev'
Requires-Dist: black ; extra == 'dev'
Requires-Dist: mypy ; extra == 'dev'
Requires-Dist: pre-commit ; extra == 'dev'
Requires-Dist: ruff ; extra == 'dev'
Requires-Dist: setuptools-scm ; extra == 'dev'
